stampy/__init__.py
stampy/__main__.py
stampy/commands.py
stampy/config.py
stampy/contextvars.py
stampy/email.py
stampy/input.py
stampy/jmap.py
stampy/sql.py
stampy/types.py
stampy/templates/happy_birthday.html
stampy_cli-0.0.1.dist-info/METADATA
stampy_cli-0.0.1.dist-info/WHEEL
stampy_cli-0.0.1.dist-info/entry_points.txt
stampy_cli-0.0.1.dist-info/licenses/LICENSE
stampy_cli-0.0.1.dist-info/RECORD
