Metadata-Version: 2.3
Name: stampy-cli
Version: 0.0.1
Summary: A system for capturing, tracking, and attending to important dates.
Project-URL: Homepage, https://gitlab.com/JoshWVS/stampy
Author-email: Joshua Simpson <josh@simpsonian.ca>
License:                     GNU AFFERO GENERAL PUBLIC LICENSE
License-File: LICENSE
Classifier: License :: OSI Approved :: GNU Affero General Public License v3
Classifier: Programming Language :: Python :: 3
Requires-Python: >=3.11
Requires-Dist: jinja2
Requires-Dist: pydantic
Requires-Dist: requests
